{"Active connections": 1594, "All-time mined DUCO": 94441708.88373779, "Current difficulty": 75000, "DUCO-S1 hashrate": "3.0 GH/s", "Duco FluffySwap price": 2.3485e-05, "Duco Furim price": 0.0, "Duco Node-S price": 0.0, "Duco PancakeSwap price": 3.58391e-05, "Duco SunSwap price": 8.911e-05, "Duco SushiSwap price": 1.51461e-05, "Duco UbeSwap price": 2.9033013345820652e-05, "Duco price": 0.0001228, "Duco price BCH": 3.358e-05, "Duco price NANO": 1.536e-05, "Duco price TRX": 1.729e-05, "Duco price XMG": 0.0001228, "Duino-Coin Server API": "github.com/revoxhere/duino-coin", "Kolka": {"Banned": 1089, "Jailed": 84}, "Last block hash": "8de4bc0b3fa1580ec7f3421feb9644fc8ead02b8", "Last sync": 1665575734.5599728, "Last update": "12/10/2022 11:55:35 (UTC)", "Mined blocks": 279368497625, "Miner distribution": {"All": 37959, "Arduino": 4364, "CPU": 2010, "ESP32": 13670, "ESP8266": 16219, "GPU": 0, "Other": 12, "Phone": 68, "RPi": 1227, "Web": 389}, "Net energy usage": "29.57 kW", "Open threads": 23, "Pool hashrate": "2967.37 MH/s", "Registered users": 80917, "Server CPU usage": 42.1, "Server RAM usage": 63.3, "Server version": 3.0, "Top 10 richest miners": ["43516260.73178132 DUCO - coinexchange", "36546079.437422335 DUCO - bscDUCO", "15965318.216999998 DUCO - Ochios", "6974991.289071771 DUCO - QQ44142894", "4075220.2860000003 DUCO - AlmarRido", "2497114.2960301787 DUCO - goddani", "2368507.0 DUCO - Brunomoyses23", "2210288.919161586 DUCO - vyrdudji", "1902668.728700292 DUCO - giveaways", "1629266.8630387518 DUCO - maticDUCO"], "XXHASH hashrate": "0 H/s"}