{
    "Server version": 1.9,
    "Active connections": 102,
    "Server CPU usage": 7.8,
    "Last update": "03/02/2021 07:22 (UTC)",
    "Pool hashrate": "6.48 MH/s",
    "Duco price": 0.005154,
    "Duco satoshi price": 13.53,
    "Registered users": 633,
    "All-time mined DUCO": 362965.15,
    "Current difficulty": 51141,
    "Mined blocks": 102281681,
    "Full last block hash": "9f4b01b65e63bf593ff47cc0f4cb3fa5df490725",
    "Last block hash": "9f4b01b65e...",
    "Top 10 richest miners": [
        "86455.9308 DUCO - xmrRohan",
        "31816.1876 DUCO - aarican",
        "21203.2225 DUCO - sabartheman",
        "16471.0186 DUCO - PHR9",
        "16335.563 DUCO - travelmode",
        "15916.0366 DUCO - MaddestHoldings",
        "12192.5476 DUCO - TOG",
        "11432.702 DUCO - drn",
        "8249.6541 DUCO - MattLancaster",
        "7862.3849 DUCO - baibaide"
    ],
    "Active workers": {
        "stanzwerck": 7,
        "TOG": 39,
        "thedoctor": 1,
        "parker": 12,
        "Raven": 1,
        "wossky": 1,
        "MagicForces": 2,
        "catalsma": 1,
        "Punixz": 5,
        "lulkas": 11,
        "JoyBed": 3,
        "criticBalance": 9,
        "Dome": 1,
        "kroko": 1,
        "EinWildesPanda": 3,
        "kmmichalskik": 1
    },
    "Miners": {
        "140418243094272": {
            "User": "stanzwerck",
            "Hashrate": 2150.0,
            "Is estimated": "False",
            "Sharetime": 1267.0,
            "Accepted": 6556,
            "Rejected": 286,
            "Diff": 3500,
            "Software": "ESP Miner v1.8",
            "Last share timestamp": "03/02/2021 07:22:42"
        },
        "140418058520320": {
            "User": "stanzwerck",
            "Hashrate": 2150.0,
            "Is estimated": "False",
            "Sharetime": 704.0,
            "Accepted": 6567,
            "Rejected": 258,
            "Diff": 3500,
            "Software": "ESP Miner v1.8",
            "Last share timestamp": "03/02/2021 07:22:42"
        },
        "140418108876544": {
            "User": "stanzwerck",
            "Hashrate": 2150.0,
            "Is estimated": "False",
            "Sharetime": 1386.0,
            "Accepted": 6490,
            "Rejected": 258,
            "Diff": 3500,
            "Software": "ESP Miner v1.8",
            "Last share timestamp": "03/02/2021 07:22:43"
        },
        "140418201130752": {
            "User": "TOG",
            "Hashrate": 1971.0,
            "Is estimated": "True",
            "Sharetime": 284.0,
            "Accepted": 6599,
            "Rejected": 0,
            "Diff": 3500,
            "Software": "Unknown",
            "Last share timestamp": "03/02/2021 07:22:42"
        },
        "140418041734912": {
            "User": "thedoctor",
            "Hashrate": 2150.0,
            "Is estimated": "False",
            "Sharetime": 454.0,
            "Accepted": 6556,
            "Rejected": 261,
            "Diff": 3500,
            "Software": "ESP Miner v1.8",
            "Last share timestamp": "03/02/2021 07:22:42"
        },
        "140418016556800": {
            "User": "TOG",
            "Hashrate": 2661.0,
            "Is estimated": "True",
            "Sharetime": 803.0,
            "Accepted": 6574,
            "Rejected": 0,
            "Diff": 3500,
            "Software": "Unknown",
            "Last share timestamp": "03/02/2021 07:22:43"
        },
        "140417982985984": {
            "User": "stanzwerck",
            "Hashrate": 2150.0,
            "Is estimated": "False",
            "Sharetime": 1356.0,
            "Accepted": 6517,
            "Rejected": 294,
            "Diff": 3500,
            "Software": "ESP Miner v1.8",
            "Last share timestamp": "03/02/2021 07:22:43"
        },
        "140417966200576": {
            "User": "parker",
            "Hashrate": 2150.0,
            "Is estimated": "False",
            "Sharetime": 38.0,
            "Accepted": 4149,
            "Rejected": 102,
            "Diff": 3500,
            "Software": "ESP Miner v1.8",
            "Last share timestamp": "03/02/2021 07:22:43"
        },
        "140418033342208": {
            "User": "parker",
            "Hashrate": 2150.0,
            "Is estimated": "False",
            "Sharetime": 1062.0,
            "Accepted": 3705,
            "Rejected": 99,
            "Diff": 3500,
            "Software": "ESP Miner v1.8",
            "Last share timestamp": "03/02/2021 07:22:41"
        },
        "140418050127616": {
            "User": "stanzwerck",
            "Hashrate": 2150.0,
            "Is estimated": "False",
            "Sharetime": 823.0,
            "Accepted": 6536,
            "Rejected": 287,
            "Diff": 3500,
            "Software": "ESP Miner v1.8",
            "Last share timestamp": "03/02/2021 07:22:43"
        },
        "140417890666240": {
            "User": "parker",
            "Hashrate": 2150.0,
            "Is estimated": "False",
            "Sharetime": 1801.0,
            "Accepted": 4136,
            "Rejected": 94,
            "Diff": 3500,
            "Software": "ESP Miner v1.8",
            "Last share timestamp": "03/02/2021 07:22:42"
        },
        "140418024949504": {
            "User": "stanzwerck",
            "Hashrate": 2150.0,
            "Is estimated": "False",
            "Sharetime": 1202.0,
            "Accepted": 6004,
            "Rejected": 233,
            "Diff": 3500,
            "Software": "ESP Miner v1.8",
            "Last share timestamp": "03/02/2021 07:22:42"
        },
        "140417924237056": {
            "User": "TOG",
            "Hashrate": 2765.0,
            "Is estimated": "True",
            "Sharetime": 1234.0,
            "Accepted": 6664,
            "Rejected": 1,
            "Diff": 3500,
            "Software": "Unknown",
            "Last share timestamp": "03/02/2021 07:22:43"
        },
        "140417907451648": {
            "User": "Raven",
            "Hashrate": 2150.0,
            "Is estimated": "False",
            "Sharetime": 150.0,
            "Accepted": 7323,
            "Rejected": 264,
            "Diff": 3500,
            "Software": "ESP Miner v1.8",
            "Last share timestamp": "03/02/2021 07:22:43"
        },
        "140417957807872": {
            "User": "TOG",
            "Hashrate": 2629.0,
            "Is estimated": "True",
            "Sharetime": 739.0,
            "Accepted": 6584,
            "Rejected": 0,
            "Diff": 3500,
            "Software": "Unknown",
            "Last share timestamp": "03/02/2021 07:22:42"
        },
        "140417999771392": {
            "User": "parker",
            "Hashrate": 1352.0,
            "Is estimated": "True",
            "Sharetime": 332.0,
            "Accepted": 4035,
            "Rejected": 85,
            "Diff": 3500,
            "Software": "Unknown",
            "Last share timestamp": "03/02/2021 07:22:42"
        },
        "140417873880832": {
            "User": "parker",
            "Hashrate": 1437.0,
            "Is estimated": "True",
            "Sharetime": 1791.0,
            "Accepted": 3982,
            "Rejected": 103,
            "Diff": 3500,
            "Software": "Unknown",
            "Last share timestamp": "03/02/2021 07:22:43"
        },
        "140418117269248": {
            "User": "wossky",
            "Hashrate": 1434.0,
            "Is estimated": "True",
            "Sharetime": 1533.0,
            "Accepted": 3902,
            "Rejected": 49,
            "Diff": 3500,
            "Software": "Unknown",
            "Last share timestamp": "03/02/2021 07:22:42"
        },
        "140417915844352": {
            "User": "TOG",
            "Hashrate": 2627.0,
            "Is estimated": "True",
            "Sharetime": 817.0,
            "Accepted": 6564,
            "Rejected": 0,
            "Diff": 3500,
            "Software": "Unknown",
            "Last share timestamp": "03/02/2021 07:22:43"
        },
        "140418066913024": {
            "User": "parker",
            "Hashrate": 2150.0,
            "Is estimated": "False",
            "Sharetime": 1286.0,
            "Accepted": 4142,
            "Rejected": 93,
            "Diff": 3500,
            "Software": "ESP Miner v1.8",
            "Last share timestamp": "03/02/2021 07:22:42"
        },
        "140418008164096": {
            "User": "parker",
            "Hashrate": 2150.0,
            "Is estimated": "False",
            "Sharetime": 261.0,
            "Accepted": 4131,
            "Rejected": 112,
            "Diff": 3500,
            "Software": "ESP Miner v1.8",
            "Last share timestamp": "03/02/2021 07:22:42"
        },
        "140417932629760": {
            "User": "parker",
            "Hashrate": 2150.0,
            "Is estimated": "False",
            "Sharetime": 2275.0,
            "Accepted": 4110,
            "Rejected": 114,
            "Diff": 3500,
            "Software": "ESP Miner v1.8",
            "Last share timestamp": "03/02/2021 07:22:43"
        },
        "140417823524608": {
            "User": "TOG",
            "Hashrate": 2245.0,
            "Is estimated": "True",
            "Sharetime": 375.0,
            "Accepted": 6602,
            "Rejected": 0,
            "Diff": 3500,
            "Software": "Unknown",
            "Last share timestamp": "03/02/2021 07:22:42"
        },
        "140417974593280": {
            "User": "parker",
            "Hashrate": 1435.0,
            "Is estimated": "True",
            "Sharetime": 2265.0,
            "Accepted": 4069,
            "Rejected": 98,
            "Diff": 3500,
            "Software": "Unknown",
            "Last share timestamp": "03/02/2021 07:22:42"
        },
        "140417798346496": {
            "User": "TOG",
            "Hashrate": 2491.0,
            "Is estimated": "True",
            "Sharetime": 580.0,
            "Accepted": 6591,
            "Rejected": 0,
            "Diff": 3500,
            "Software": "Unknown",
            "Last share timestamp": "03/02/2021 07:22:43"
        },
        "140417789953792": {
            "User": "TOG",
            "Hashrate": 2401.0,
            "Is estimated": "True",
            "Sharetime": 473.0,
            "Accepted": 6630,
            "Rejected": 0,
            "Diff": 3500,
            "Software": "Unknown",
            "Last share timestamp": "03/02/2021 07:22:43"
        },
        "140417815131904": {
            "User": "TOG",
            "Hashrate": 2735.0,
            "Is estimated": "True",
            "Sharetime": 1123.0,
            "Accepted": 6602,
            "Rejected": 0,
            "Diff": 3500,
            "Software": "Unknown",
            "Last share timestamp": "03/02/2021 07:22:43"
        },
        "140417991378688": {
            "User": "TOG",
            "Hashrate": 2622.0,
            "Is estimated": "True",
            "Sharetime": 747.0,
            "Accepted": 6549,
            "Rejected": 0,
            "Diff": 3500,
            "Software": "Unknown",
            "Last share timestamp": "03/02/2021 07:22:42"
        },
        "140417781561088": {
            "User": "TOG",
            "Hashrate": 2673.0,
            "Is estimated": "True",
            "Sharetime": 878.0,
            "Accepted": 6593,
            "Rejected": 0,
            "Diff": 3500,
            "Software": "Unknown",
            "Last share timestamp": "03/02/2021 07:22:42"
        },
        "140417831917312": {
            "User": "TOG",
            "Hashrate": 2346.0,
            "Is estimated": "True",
            "Sharetime": 413.0,
            "Accepted": 6535,
            "Rejected": 0,
            "Diff": 3500,
            "Software": "Unknown",
            "Last share timestamp": "03/02/2021 07:22:43"
        },
        "140417949415168": {
            "User": "TOG",
            "Hashrate": 2760.0,
            "Is estimated": "True",
            "Sharetime": 1248.0,
            "Accepted": 6622,
            "Rejected": 0,
            "Diff": 3500,
            "Software": "Unknown",
            "Last share timestamp": "03/02/2021 07:22:42"
        },
        "140417840310016": {
            "User": "TOG",
            "Hashrate": 689.0,
            "Is estimated": "True",
            "Sharetime": 116.0,
            "Accepted": 6671,
            "Rejected": 0,
            "Diff": 3500,
            "Software": "Unknown",
            "Last share timestamp": "03/02/2021 07:22:43"
        },
        "140417865488128": {
            "User": "TOG",
            "Hashrate": 954.0,
            "Is estimated": "True",
            "Sharetime": 133.0,
            "Accepted": 6606,
            "Rejected": 0,
            "Diff": 3500,
            "Software": "Unknown",
            "Last share timestamp": "03/02/2021 07:22:43"
        },
        "140417899058944": {
            "User": "TOG",
            "Hashrate": 2339.0,
            "Is estimated": "True",
            "Sharetime": 439.0,
            "Accepted": 6555,
            "Rejected": 0,
            "Diff": 3500,
            "Software": "Unknown",
            "Last share timestamp": "03/02/2021 07:22:42"
        },
        "140417731204864": {
            "User": "TOG",
            "Hashrate": 1804.0,
            "Is estimated": "True",
            "Sharetime": 235.0,
            "Accepted": 6597,
            "Rejected": 0,
            "Diff": 3500,
            "Software": "Unknown",
            "Last share timestamp": "03/02/2021 07:22:42"
        },
        "140417882273536": {
            "User": "parker",
            "Hashrate": 2150.0,
            "Is estimated": "False",
            "Sharetime": 152.0,
            "Accepted": 4087,
            "Rejected": 104,
            "Diff": 3500,
            "Software": "ESP Miner v1.8",
            "Last share timestamp": "03/02/2021 07:22:42"
        },
        "140417747990272": {
            "User": "TOG",
            "Hashrate": 2097.0,
            "Is estimated": "True",
            "Sharetime": 309.0,
            "Accepted": 6604,
            "Rejected": 0,
            "Diff": 3500,
            "Software": "Unknown",
            "Last share timestamp": "03/02/2021 07:22:42"
        },
        "140417857095424": {
            "User": "TOG",
            "Hashrate": 1378.0,
            "Is estimated": "True",
            "Sharetime": 164.0,
            "Accepted": 6617,
            "Rejected": 0,
            "Diff": 3500,
            "Software": "Unknown",
            "Last share timestamp": "03/02/2021 07:22:42"
        },
        "140417722812160": {
            "User": "TOG",
            "Hashrate": 2508.0,
            "Is estimated": "True",
            "Sharetime": 558.0,
            "Accepted": 6674,
            "Rejected": 0,
            "Diff": 3500,
            "Software": "Unknown",
            "Last share timestamp": "03/02/2021 07:22:42"
        },
        "140417706026752": {
            "User": "TOG",
            "Hashrate": 2770.0,
            "Is estimated": "True",
            "Sharetime": 1244.0,
            "Accepted": 6649,
            "Rejected": 0,
            "Diff": 3500,
            "Software": "Unknown",
            "Last share timestamp": "03/02/2021 07:22:42"
        },
        "140417806739200": {
            "User": "TOG",
            "Hashrate": 1262.0,
            "Is estimated": "True",
            "Sharetime": 164.0,
            "Accepted": 6660,
            "Rejected": 0,
            "Diff": 3500,
            "Software": "Unknown",
            "Last share timestamp": "03/02/2021 07:22:42"
        },
        "140417848702720": {
            "User": "MagicForces",
            "Hashrate": 2150.0,
            "Is estimated": "False",
            "Sharetime": 1761.0,
            "Accepted": 4045,
            "Rejected": 77,
            "Diff": 3500,
            "Software": "ESP Miner v1.8",
            "Last share timestamp": "03/02/2021 07:22:41"
        },
        "140417941022464": {
            "User": "parker",
            "Hashrate": 2150.0,
            "Is estimated": "False",
            "Sharetime": 2084.0,
            "Accepted": 4046,
            "Rejected": 116,
            "Diff": 3500,
            "Software": "ESP Miner v1.8",
            "Last share timestamp": "03/02/2021 07:22:42"
        },
        "140417647277824": {
            "User": "TOG",
            "Hashrate": 2648.0,
            "Is estimated": "True",
            "Sharetime": 797.0,
            "Accepted": 6498,
            "Rejected": 0,
            "Diff": 3500,
            "Software": "Unknown",
            "Last share timestamp": "03/02/2021 07:22:43"
        },
        "140417714419456": {
            "User": "TOG",
            "Hashrate": 2749.0,
            "Is estimated": "True",
            "Sharetime": 1163.0,
            "Accepted": 6671,
            "Rejected": 0,
            "Diff": 3500,
            "Software": "Unknown",
            "Last share timestamp": "03/02/2021 07:22:42"
        },
        "140417638885120": {
            "User": "TOG",
            "Hashrate": 2203.0,
            "Is estimated": "True",
            "Sharetime": 353.0,
            "Accepted": 6537,
            "Rejected": 0,
            "Diff": 3500,
            "Software": "Unknown",
            "Last share timestamp": "03/02/2021 07:22:43"
        },
        "140417664063232": {
            "User": "TOG",
            "Hashrate": 2758.0,
            "Is estimated": "True",
            "Sharetime": 1224.0,
            "Accepted": 6557,
            "Rejected": 0,
            "Diff": 3500,
            "Software": "Unknown",
            "Last share timestamp": "03/02/2021 07:22:42"
        },
        "140417596921600": {
            "User": "TOG",
            "Hashrate": 2035.0,
            "Is estimated": "True",
            "Sharetime": 281.0,
            "Accepted": 6660,
            "Rejected": 0,
            "Diff": 3500,
            "Software": "Unknown",
            "Last share timestamp": "03/02/2021 07:22:42"
        },
        "140417756382976": {
            "User": "TOG",
            "Hashrate": 2734.0,
            "Is estimated": "True",
            "Sharetime": 1014.0,
            "Accepted": 6608,
            "Rejected": 0,
            "Diff": 3500,
            "Software": "Unknown",
            "Last share timestamp": "03/02/2021 07:22:42"
        },
        "140417739597568": {
            "User": "TOG",
            "Hashrate": 2663.0,
            "Is estimated": "True",
            "Sharetime": 840.0,
            "Accepted": 6621,
            "Rejected": 0,
            "Diff": 3500,
            "Software": "Unknown",
            "Last share timestamp": "03/02/2021 07:22:42"
        },
        "140417680848640": {
            "User": "TOG",
            "Hashrate": 475.0,
            "Is estimated": "True",
            "Sharetime": 103.0,
            "Accepted": 6615,
            "Rejected": 1,
            "Diff": 3500,
            "Software": "Unknown",
            "Last share timestamp": "03/02/2021 07:22:43"
        },
        "140417764775680": {
            "User": "TOG",
            "Hashrate": 2622.0,
            "Is estimated": "True",
            "Sharetime": 777.0,
            "Accepted": 6482,
            "Rejected": 0,
            "Diff": 3500,
            "Software": "Unknown",
            "Last share timestamp": "03/02/2021 07:22:42"
        },
        "140417672455936": {
            "User": "TOG",
            "Hashrate": 2748.0,
            "Is estimated": "True",
            "Sharetime": 1182.0,
            "Accepted": 6587,
            "Rejected": 0,
            "Diff": 3500,
            "Software": "Unknown",
            "Last share timestamp": "03/02/2021 07:22:42"
        },
        "140417554958080": {
            "User": "TOG",
            "Hashrate": 2687.0,
            "Is estimated": "True",
            "Sharetime": 880.0,
            "Accepted": 6516,
            "Rejected": 0,
            "Diff": 3500,
            "Software": "Unknown",
            "Last share timestamp": "03/02/2021 07:22:42"
        },
        "140417605314304": {
            "User": "TOG",
            "Hashrate": 2529.0,
            "Is estimated": "True",
            "Sharetime": 636.0,
            "Accepted": 6656,
            "Rejected": 0,
            "Diff": 3500,
            "Software": "Unknown",
            "Last share timestamp": "03/02/2021 07:22:42"
        },
        "140417613707008": {
            "User": "TOG",
            "Hashrate": 2735.0,
            "Is estimated": "True",
            "Sharetime": 1023.0,
            "Accepted": 6601,
            "Rejected": 0,
            "Diff": 3500,
            "Software": "Unknown",
            "Last share timestamp": "03/02/2021 07:22:42"
        },
        "140417571743488": {
            "User": "TOG",
            "Hashrate": 2690.0,
            "Is estimated": "True",
            "Sharetime": 948.0,
            "Accepted": 6589,
            "Rejected": 0,
            "Diff": 3500,
            "Software": "Unknown",
            "Last share timestamp": "03/02/2021 07:22:42"
        },
        "140417697634048": {
            "User": "MagicForces",
            "Hashrate": 2150.0,
            "Is estimated": "False",
            "Sharetime": 494.0,
            "Accepted": 4047,
            "Rejected": 73,
            "Diff": 3500,
            "Software": "ESP Miner v1.8",
            "Last share timestamp": "03/02/2021 07:22:42"
        },
        "140417504601856": {
            "User": "TOG",
            "Hashrate": 2754.0,
            "Is estimated": "True",
            "Sharetime": 1179.0,
            "Accepted": 6486,
            "Rejected": 0,
            "Diff": 3500,
            "Software": "Unknown",
            "Last share timestamp": "03/02/2021 07:22:42"
        },
        "140417689241344": {
            "User": "catalsma",
            "Hashrate": 135.0,
            "Is estimated": "False",
            "Sharetime": 3014.0,
            "Accepted": 2733,
            "Rejected": 0,
            "Diff": 400,
            "Software": "Official AVR Miner v1.9",
            "Last share timestamp": "03/02/2021 07:22:41"
        },
        "140417487816448": {
            "User": "Punixz",
            "Hashrate": 2150.0,
            "Is estimated": "False",
            "Sharetime": 144.0,
            "Accepted": 7319,
            "Rejected": 249,
            "Diff": 3500,
            "Software": "ESP Miner v1.8",
            "Last share timestamp": "03/02/2021 07:22:43"
        },
        "140417521387264": {
            "User": "TOG",
            "Hashrate": 2644.0,
            "Is estimated": "True",
            "Sharetime": 783.0,
            "Accepted": 6623,
            "Rejected": 0,
            "Diff": 3500,
            "Software": "Unknown",
            "Last share timestamp": "03/02/2021 07:22:42"
        },
        "140417622099712": {
            "User": "TOG",
            "Hashrate": 2733.0,
            "Is estimated": "True",
            "Sharetime": 1037.0,
            "Accepted": 6508,
            "Rejected": 0,
            "Diff": 3500,
            "Software": "Unknown",
            "Last share timestamp": "03/02/2021 07:22:42"
        },
        "140417529779968": {
            "User": "stanzwerck",
            "Hashrate": 2150.0,
            "Is estimated": "False",
            "Sharetime": 2040.0,
            "Accepted": 3573,
            "Rejected": 67,
            "Diff": 3500,
            "Software": "ESP Miner v1.8",
            "Last share timestamp": "03/02/2021 07:22:42"
        },
        "140417429067520": {
            "User": "lulkas",
            "Hashrate": 83987.0,
            "Is estimated": "False",
            "Sharetime": 603020.0,
            "Accepted": 3,
            "Rejected": 0,
            "Diff": 51006,
            "Software": "Official Python Miner v2.0",
            "Last share timestamp": "03/02/2021 06:36:03"
        },
        "140417588528896": {
            "User": "lulkas",
            "Hashrate": 84079.0,
            "Is estimated": "False",
            "Sharetime": 602817.0,
            "Accepted": 3,
            "Rejected": 0,
            "Diff": 51005,
            "Software": "Official Python Miner v2.0",
            "Last share timestamp": "03/02/2021 06:35:36"
        },
        "140417336747776": {
            "User": "JoyBed",
            "Hashrate": 14853.0,
            "Is estimated": "False",
            "Sharetime": 959.0,
            "Accepted": 637,
            "Rejected": 4,
            "Diff": 3500,
            "Software": "ESP Miner v1.8",
            "Last share timestamp": "03/02/2021 06:24:49"
        },
        "140417403889408": {
            "User": "criticBalance",
            "Hashrate": 98535.0,
            "Is estimated": "False",
            "Sharetime": 1359.0,
            "Accepted": 639,
            "Rejected": 0,
            "Diff": 4000,
            "Software": "Official Webminer v2.0",
            "Last share timestamp": "03/02/2021 07:22:37"
        },
        "140417353533184": {
            "User": "criticBalance",
            "Hashrate": 24766.0,
            "Is estimated": "False",
            "Sharetime": 550.0,
            "Accepted": 530,
            "Rejected": 0,
            "Diff": 4000,
            "Software": "Official Webminer v2.0",
            "Last share timestamp": "03/02/2021 07:22:37"
        },
        "140417630492416": {
            "User": "criticBalance",
            "Hashrate": 24219.0,
            "Is estimated": "False",
            "Sharetime": 504.0,
            "Accepted": 1000,
            "Rejected": 0,
            "Diff": 4000,
            "Software": "Official Webminer v2.0",
            "Last share timestamp": "03/02/2021 07:22:39"
        },
        "140417395496704": {
            "User": "criticBalance",
            "Hashrate": 295231.0,
            "Is estimated": "False",
            "Sharetime": 5196.0,
            "Accepted": 927,
            "Rejected": 0,
            "Diff": 4000,
            "Software": "Official Webminer v2.0",
            "Last share timestamp": "03/02/2021 07:22:38"
        },
        "140418226308864": {
            "User": "criticBalance",
            "Hashrate": 10190.0,
            "Is estimated": "False",
            "Sharetime": 4919.0,
            "Accepted": 527,
            "Rejected": 0,
            "Diff": 4000,
            "Software": "Official Webminer v2.0",
            "Last share timestamp": "03/02/2021 07:22:42"
        },
        "140417319962368": {
            "User": "criticBalance",
            "Hashrate": 376311.0,
            "Is estimated": "False",
            "Sharetime": 4804.0,
            "Accepted": 625,
            "Rejected": 0,
            "Diff": 4000,
            "Software": "Official Webminer v2.0",
            "Last share timestamp": "03/02/2021 07:22:42"
        },
        "140417471031040": {
            "User": "criticBalance",
            "Hashrate": 342555.0,
            "Is estimated": "False",
            "Sharetime": 8815.0,
            "Accepted": 568,
            "Rejected": 0,
            "Diff": 4000,
            "Software": "Official Webminer v2.0",
            "Last share timestamp": "03/02/2021 07:22:39"
        },
        "140417361925888": {
            "User": "criticBalance",
            "Hashrate": 19281.0,
            "Is estimated": "False",
            "Sharetime": 1404.0,
            "Accepted": 600,
            "Rejected": 0,
            "Diff": 4000,
            "Software": "Official Webminer v2.0",
            "Last share timestamp": "03/02/2021 07:22:42"
        },
        "140417328355072": {
            "User": "criticBalance",
            "Hashrate": 6174.0,
            "Is estimated": "False",
            "Sharetime": 1338.0,
            "Accepted": 603,
            "Rejected": 0,
            "Diff": 4000,
            "Software": "Official Webminer v2.0",
            "Last share timestamp": "03/02/2021 07:22:39"
        },
        "140417269606144": {
            "User": "Dome",
            "Hashrate": 306137.0,
            "Is estimated": "False",
            "Sharetime": 1289.0,
            "Accepted": 2579,
            "Rejected": 0,
            "Diff": 4000,
            "Software": "Official Webminer v2.0",
            "Last share timestamp": "03/02/2021 07:22:42"
        },
        "140417261213440": {
            "User": "JoyBed",
            "Hashrate": 19508.0,
            "Is estimated": "False",
            "Sharetime": 2949.0,
            "Accepted": 2173,
            "Rejected": 16,
            "Diff": 3500,
            "Software": "ESP Miner v1.8",
            "Last share timestamp": "03/02/2021 07:07:09"
        },
        "140417445852928": {
            "User": "lulkas",
            "Hashrate": 83467.0,
            "Is estimated": "False",
            "Sharetime": 615355.0,
            "Accepted": 5,
            "Rejected": 0,
            "Diff": 51080,
            "Software": "Official Python Miner v2.0",
            "Last share timestamp": "03/02/2021 07:07:00"
        },
        "140418217916160": {
            "User": "kroko",
            "Hashrate": 55465.0,
            "Is estimated": "False",
            "Sharetime": 46480.0,
            "Accepted": 29,
            "Rejected": 0,
            "Diff": 51137,
            "Software": "Official Python Miner v1.9",
            "Last share timestamp": "03/02/2021 07:21:35"
        },
        "140417479423744": {
            "User": "parker",
            "Hashrate": 577405.0,
            "Is estimated": "False",
            "Sharetime": 8286.0,
            "Accepted": 306,
            "Rejected": 0,
            "Diff": 51141,
            "Software": "Official Python Miner v1.9",
            "Last share timestamp": "03/02/2021 07:22:38"
        },
        "140417538172672": {
            "User": "EinWildesPanda",
            "Hashrate": 298174.0,
            "Is estimated": "False",
            "Sharetime": 10129.0,
            "Accepted": 191,
            "Rejected": 0,
            "Diff": 51141,
            "Software": "nonceMiner_v1.2.1",
            "Last share timestamp": "03/02/2021 07:22:42"
        },
        "140418100483840": {
            "User": "EinWildesPanda",
            "Hashrate": 298128.0,
            "Is estimated": "False",
            "Sharetime": 11755.0,
            "Accepted": 185,
            "Rejected": 0,
            "Diff": 51141,
            "Software": "nonceMiner_v1.2.1",
            "Last share timestamp": "03/02/2021 07:22:37"
        },
        "140417580136192": {
            "User": "EinWildesPanda",
            "Hashrate": 299606.0,
            "Is estimated": "False",
            "Sharetime": 14075.0,
            "Accepted": 197,
            "Rejected": 0,
            "Diff": 51141,
            "Software": "nonceMiner_v1.2.1",
            "Last share timestamp": "03/02/2021 07:22:41"
        },
        "140417773168384": {
            "User": "lulkas",
            "Hashrate": 83716.0,
            "Is estimated": "False",
            "Sharetime": 10462.0,
            "Accepted": 3,
            "Rejected": 0,
            "Diff": 51123,
            "Software": "Official Python Miner v2.0",
            "Last share timestamp": "03/02/2021 07:15:22"
        },
        "140417512994560": {
            "User": "Punixz",
            "Hashrate": 535250.0,
            "Is estimated": "False",
            "Sharetime": 10451.0,
            "Accepted": 159,
            "Rejected": 0,
            "Diff": 51141,
            "Software": "Official Python Miner v1.9",
            "Last share timestamp": "03/02/2021 07:22:37"
        },
        "140417437460224": {
            "User": "Punixz",
            "Hashrate": 496222.0,
            "Is estimated": "False",
            "Sharetime": 3218.0,
            "Accepted": 146,
            "Rejected": 0,
            "Diff": 51141,
            "Software": "Official Python Miner v1.9",
            "Last share timestamp": "03/02/2021 07:22:42"
        },
        "140417563350784": {
            "User": "lulkas",
            "Hashrate": 83862.0,
            "Is estimated": "False",
            "Sharetime": 616104.0,
            "Accepted": 2,
            "Rejected": 0,
            "Diff": 51116,
            "Software": "Official Python Miner v2.0",
            "Last share timestamp": "03/02/2021 07:22:20"
        },
        "140418083698432": {
            "User": "Punixz",
            "Hashrate": 544766.0,
            "Is estimated": "False",
            "Sharetime": 4066.0,
            "Accepted": 160,
            "Rejected": 0,
            "Diff": 51141,
            "Software": "Official Python Miner v1.9",
            "Last share timestamp": "03/02/2021 07:22:36"
        },
        "140418092091136": {
            "User": "Punixz",
            "Hashrate": 552734.0,
            "Is estimated": "False",
            "Sharetime": 1412.0,
            "Accepted": 137,
            "Rejected": 0,
            "Diff": 51141,
            "Software": "Official Python Miner v1.9",
            "Last share timestamp": "03/02/2021 07:22:43"
        },
        "140417387104000": {
            "User": "kmmichalskik",
            "Hashrate": 202302.0,
            "Is estimated": "False",
            "Sharetime": 665.0,
            "Accepted": 515,
            "Rejected": 0,
            "Diff": 4000,
            "Software": "Official Webminer v2.0",
            "Last share timestamp": "03/02/2021 07:22:42"
        },
        "140417311569664": {
            "User": "lulkas",
            "Hashrate": 83459.0,
            "Is estimated": "False",
            "Sharetime": 67127.0,
            "Accepted": 3,
            "Rejected": 0,
            "Diff": 51132,
            "Software": "Official Python Miner v2.0",
            "Last share timestamp": "03/02/2021 07:19:52"
        },
        "140417655670528": {
            "User": "lulkas",
            "Hashrate": 82787.0,
            "Is estimated": "False",
            "Sharetime": 218461.0,
            "Accepted": 1,
            "Rejected": 0,
            "Diff": 51117,
            "Software": "Official Python Miner v2.0",
            "Last share timestamp": "03/02/2021 07:16:13"
        },
        "140418209523456": {
            "User": "lulkas",
            "Hashrate": 85610.0,
            "Is estimated": "False",
            "Sharetime": 369989.0,
            "Accepted": 0,
            "Rejected": 0,
            "Diff": 51105,
            "Software": "Official Python Miner v2.0",
            "Last share timestamp": "03/02/2021 07:13:41"
        },
        "140417454245632": {
            "User": "JoyBed",
            "Hashrate": 18752.0,
            "Is estimated": "False",
            "Sharetime": 8528.0,
            "Accepted": 7,
            "Rejected": 0,
            "Diff": 3500,
            "Software": "ESP Miner v1.8",
            "Last share timestamp": "03/02/2021 07:14:06"
        },
        "140417345140480": {
            "User": "lulkas",
            "Hashrate": 83459.0,
            "Is estimated": "False",
            "Sharetime": 213982.0,
            "Accepted": 2,
            "Rejected": 0,
            "Diff": 51126,
            "Software": "Official Python Miner v2.0",
            "Last share timestamp": "03/02/2021 07:19:52"
        },
        "140417546565376": {
            "User": "lulkas",
            "Hashrate": 82599.0,
            "Is estimated": "False",
            "Sharetime": 541790.0,
            "Accepted": 0,
            "Rejected": 0,
            "Diff": 51105,
            "Software": "Official Python Miner v2.0",
            "Last share timestamp": "03/02/2021 07:16:33"
        },
        "140417462638336": {
            "User": "lulkas",
            "Hashrate": 83883.0,
            "Is estimated": "False",
            "Sharetime": 239907.0,
            "Accepted": 2,
            "Rejected": 0,
            "Diff": 51131,
            "Software": "Official Python Miner v2.0",
            "Last share timestamp": "03/02/2021 07:22:13"
        }
    }
}